clickforward.py
clickforward-0.0.1.dist-info/LICENSE
clickforward-0.0.1.dist-info/METADATA
clickforward-0.0.1.dist-info/WHEEL
clickforward-0.0.1.dist-info/top_level.txt
clickforward-0.0.1.dist-info/RECORD
