Metadata-Version: 2.1
Name: clickforward
Version: 0.0.1
Summary: Forward all arguments using click without any parsing and without -
Author: Kamil Cukrowski
License: MIT
Project-URL: homepage, https://github.com/Kamilcuk/clickforward
Project-URL: repository, https://github.com/Kamilcuk/clickforward
Project-URL: documentation, https://github.com/Kamilcuk/clickforward
License-File: LICENSE
Requires-Dist: typing-extensions
Requires-Dist: click
Provides-Extra: test
Requires-Dist: pytest ; extra == 'test'
